BasedUtilities2.py
README.md
setup.py
BasedUtilities2/BasedUtilities2.py
BasedUtilities2/__init__.py
BasedUtilities2.egg-info/PKG-INFO
BasedUtilities2.egg-info/SOURCES.txt
BasedUtilities2.egg-info/dependency_links.txt
BasedUtilities2.egg-info/requires.txt
BasedUtilities2.egg-info/top_level.txt