Metadata-Version: 1.0
Name: BasedUtilities2
Version: 0.0.3
Summary: UNKNOWN
Home-page: UNKNOWN
Author: BasedUtilities2
Author-email: BasedUtilities2@BasedUtilitiesAddress.com
License: Python. Free To View And Purchase With Attribution To The Author.
Platform: UNKNOWN
